{"57093_BL2_inv_3D_met.pdf":{"fileName":"57093_BL2_inv_3D_met.pdf","state":"pass","message":"05.03.2026, 12:19:49 Файл отправлен в папку CMYK_PP_Black2_Invers_met"},"59013_BL2_inv_3D_met.pdf":{"fileName":"59013_BL2_inv_3D_met.pdf","state":"pass","message":"05.03.2026, 12:19:38 Файл отправлен в папку CMYK_PP_Black2_Invers_met"},"CUT_2415.pdf":{"fileName":"CUT_2415.pdf","state":"pass","message":"05.03.2026, 12:19:20 Файл отправлен в папку CUT"},"46414_CMY.pdf":{"fileName":"46414_CMY.pdf","state":"pass","message":"05.03.2026, 11:34:56 Файл отправлен в папку CMY_PP"},"80278_CMY_Met.pdf":{"fileName":"80278_CMY_Met.pdf","state":"pass","message":"05.03.2026, 11:45:32 Файл отправлен в папку CMY_MET"},"80277_CMY_Met.pdf":{"fileName":"80277_CMY_Met.pdf","state":"pass","message":"05.03.2026, 11:45:32 Файл отправлен в папку CMY_MET"},"CUT_2766.pdf":{"fileName":"CUT_2766.pdf","state":"pass","message":"05.03.2026, 11:46:18 Файл отправлен в папку CUT"},"63678_CMYK.pdf":{"fileName":"63678_CMYK.pdf","state":"pass","message":"05.03.2026, 12:07:16 Файл отправлен в папку CMYK_PP"},"42877_CMYK.pdf":{"fileName":"42877_CMYK.pdf","state":"pass","message":"05.03.2026, 12:11:23 Файл отправлен в папку CMYK_PP"},"45621_CMYK.pdf":{"fileName":"45621_CMYK.pdf","state":"pass","message":"05.03.2026, 12:24:24 Файл отправлен в папку CMYK_PP"},"38838_CMYK.pdf":{"fileName":"38838_CMYK.pdf","state":"pass","message":"05.03.2026, 12:24:33 Файл отправлен в папку CMYK_PP"},"40594_CMYK.pdf":{"fileName":"40594_CMYK.pdf","state":"pass","message":"05.03.2026, 12:24:44 Файл отправлен в папку CMYK_PP"},"69552_CMYK.pdf":{"fileName":"69552_CMYK.pdf","state":"pass","message":"05.03.2026, 12:24:51 Файл отправлен в папку CMYK_PP"},"63679_CMYK.pdf":{"fileName":"63679_CMYK.pdf","state":"pass","message":"05.03.2026, 12:25:06 Файл отправлен в папку CMYK_PP"},"47544_52471_29652_31093_81024_BL2.pdf":{"fileName":"47544_52471_29652_31093_81024_BL2.pdf","state":"pass","message":"05.03.2026, 12:35:51 Файл отправлен в папку CMYK_PP_Black2"},"62254_59411_81023_68352_BL2.pdf":{"fileName":"62254_59411_81023_68352_BL2.pdf","state":"pass","message":"05.03.2026, 13:30:03 Файл отправлен в папку CMYK_PP_Black2"},"23832_levo_CMYK.pdf":{"fileName":"23832_levo_CMYK.pdf","state":"pass","message":"05.03.2026, 14:29:44 Файл отправлен в папку CMYK_PP"},"42184_levo_CMYK.pdf":{"fileName":"42184_levo_CMYK.pdf","state":"pass","message":"05.03.2026, 14:31:12 Файл отправлен в папку CMYK_PP"},"80930_levo_CMYK.pdf":{"fileName":"80930_levo_CMYK.pdf","state":"pass","message":"05.03.2026, 14:32:13 Файл отправлен в папку CMYK_PP"},"80931_levo_CMYK.pdf":{"fileName":"80931_levo_CMYK.pdf","state":"pass","message":"05.03.2026, 14:32:54 Файл отправлен в папку CMYK_PP"},"27344_levo_CMYK.pdf":{"fileName":"27344_levo_CMYK.pdf","state":"pass","message":"05.03.2026, 14:35:08 Файл отправлен в папку CMYK_PP"},"25848_levo_CMYK.pdf":{"fileName":"25848_levo_CMYK.pdf","state":"pass","message":"05.03.2026, 14:35:21 Файл отправлен в папку CMYK_PP"},"25244_levo_CMYK.pdf":{"fileName":"25244_levo_CMYK.pdf","state":"pass","message":"05.03.2026, 14:36:04 Файл отправлен в папку CMYK_PP"},"25438_levo_CMYK.pdf":{"fileName":"25438_levo_CMYK.pdf","state":"pass","message":"05.03.2026, 14:36:21 Файл отправлен в папку CMYK_PP"},"47765_levo_CMYK.pdf":{"fileName":"47765_levo_CMYK.pdf","state":"pass","message":"05.03.2026, 14:36:31 Файл отправлен в папку CMYK_PP"},"46649_levo_CMY.pdf":{"fileName":"46649_levo_CMY.pdf","state":"pass","message":"05.03.2026, 14:36:42 Файл отправлен в папку CMY_PP"},"81033_levo_CMYK.pdf":{"fileName":"81033_levo_CMYK.pdf","state":"pass","message":"05.03.2026, 14:39:42 Файл отправлен в папку CMYK_PP"},"37914_levo_CMYK.pdf":{"fileName":"37914_levo_CMYK.pdf","state":"pass","message":"05.03.2026, 14:49:40 Файл отправлен в папку CMYK_PP"},"Test_05.03.26_AlfaHim_CMYK.pdf":{"fileName":"Test_05.03.26_AlfaHim_CMYK.pdf","state":"pass","message":"05.03.2026, 14:55:10 Файл отправлен в папку _Proba_CMYK_PP"},"47344(L)_CMY.pdf":{"fileName":"47344(L)_CMY.pdf","state":"pass","message":"05.03.2026, 15:19:18 Файл отправлен в папку CMY_PP"},"44815(L)_CMYK.pdf":{"fileName":"44815(L)_CMYK.pdf","state":"pass","message":"05.03.2026, 15:19:36 Файл отправлен в папку CMYK_PP"},"47343(L)_CMYK.pdf":{"fileName":"47343(L)_CMYK.pdf","state":"pass","message":"05.03.2026, 15:20:29 Файл отправлен в папку CMYK_PP"},"42886_CMYK.pdf":{"fileName":"42886_CMYK.pdf","state":"pass","message":"05.03.2026, 15:37:12 Файл отправлен в папку CMYK_PP"},"34369_CMYK.pdf":{"fileName":"34369_CMYK.pdf","state":"pass","message":"05.03.2026, 15:38:34 Файл отправлен в папку CMYK_PP"},"27352_CMYK.pdf":{"fileName":"27352_CMYK.pdf","state":"pass","message":"05.03.2026, 15:39:09 Файл отправлен в папку CMYK_PP"},"Test_05.03_Farben_CMYK.pdf":{"fileName":"Test_05.03_Farben_CMYK.pdf","state":"pass","message":"05.03.2026, 15:40:06 Файл отправлен в папку _Proba_CMYK_PP"}}